<?xml version="1.0" encoding="utf-8" ?>
<dwsync>
<file name="bottombarre.png" server="ns2279598.ovh.net" local="130396572000000000" remote="130704808800000000" Dst="1" />
<file name="boutonbas.png" server="ns2279598.ovh.net" local="130398300000000000" remote="130704808800000000" Dst="1" />
<file name="boutonbashover.png" server="ns2279598.ovh.net" local="130398300000000000" remote="130704808800000000" Dst="1" />
<file name="course_schedule_banner.png" server="ns2279598.ovh.net" local="130398300000000000" remote="130704808800000000" Dst="1" />
<file name="dayofweek.png" server="ns2279598.ovh.net" local="130395708000000000" remote="130704808800000000" Dst="1" />
<file name="doriszucs.png" server="ns2279598.ovh.net" local="130398300000000000" remote="130704808800000000" Dst="1" />
<file name="firstweek.png" server="ns2279598.ovh.net" local="130396572000000000" remote="130704808800000000" Dst="1" />
<file name="footer_img_admissions.jpg" server="ns2279598.ovh.net" local="130400892000000000" remote="130704808800000000" Dst="1" />
<file name="footer_img_overview.jpg" server="ns2279598.ovh.net" local="130400892000000000" remote="130704808800000000" Dst="1" />
<file name="footer_img_schedule.png" server="ns2279598.ovh.net" local="130400892000000000" remote="130704808800000000" Dst="1" />
<file name="footer_img_testimonials.jpg" server="ns2279598.ovh.net" local="130400892000000000" remote="130704808800000000" Dst="1" />
<file name="fourthweek.png" server="ns2279598.ovh.net" local="130396572000000000" remote="130704808800000000" Dst="1" />
<file name="homepagebanner.png" server="ns2279598.ovh.net" local="130396572000000000" remote="130704808800000000" Dst="1" />
<file name="homepagepic.png" server="ns2279598.ovh.net" local="130396572000000000" remote="130704808800000000" Dst="1" />
<file name="imgweek1.png" server="ns2279598.ovh.net" local="130396572000000000" remote="130704808800000000" Dst="1" />
<file name="imgweek2.png" server="ns2279598.ovh.net" local="130396572000000000" remote="130704808800000000" Dst="1" />
<file name="imgweek3.png" server="ns2279598.ovh.net" local="130396572000000000" remote="130704808800000000" Dst="1" />
<file name="imgweek4.png" server="ns2279598.ovh.net" local="130396572000000000" remote="130704808800000000" Dst="1" />
<file name="micheleweiss.png" server="ns2279598.ovh.net" local="130398300000000000" remote="130704808800000000" Dst="1" />
<file name="morebutton.png" server="ns2279598.ovh.net" local="130396572000000000" remote="130704808800000000" Dst="1" />
<file name="morebutton2.png" server="ns2279598.ovh.net" local="130396572000000000" remote="130704808800000000" Dst="1" />
<file name="morebutton3.png" server="ns2279598.ovh.net" local="130396572000000000" remote="130704808800000000" Dst="1" />
<file name="morebutton4.png" server="ns2279598.ovh.net" local="130396572000000000" remote="130704808800000000" Dst="1" />
<file name="overviewpic.jpg" server="ns2279598.ovh.net" local="130400892000000000" remote="130704808800000000" Dst="1" />
<file name="scheduleicon.png" server="ns2279598.ovh.net" local="130397436000000000" remote="130704808800000000" Dst="1" />
<file name="schedulepic.png" server="ns2279598.ovh.net" local="130395708000000000" remote="130704808800000000" Dst="1" />
<file name="secondweek.png" server="ns2279598.ovh.net" local="130396572000000000" remote="130704808800000000" Dst="1" />
<file name="soulignage.png" server="ns2279598.ovh.net" local="130397436000000000" remote="130704808800000000" Dst="1" />
<file name="thirdweek.png" server="ns2279598.ovh.net" local="130396572000000000" remote="130704808800000000" Dst="1" />
<file name="titre_fondbleu.png" server="ns2279598.ovh.net" local="130397436000000000" remote="130704808800000000" Dst="1" />
<file name="titre_fondrouge.png" server="ns2279598.ovh.net" local="130397436000000000" remote="130704808800000000" Dst="1" />
<file name="top_banner_fees.png" server="ns2279598.ovh.net" local="130398300000000000" remote="130704808800000000" Dst="1" />
<file name="top_banner_testimonies.png" server="ns2279598.ovh.net" local="130398300000000000" remote="130704808800000000" Dst="1" />
<file name="topbarre.png" server="ns2279598.ovh.net" local="130396572000000000" remote="130704808800000000" Dst="1" />
<file name="vazquez.png" server="ns2279598.ovh.net" local="130400892000000000" remote="130704808800000000" Dst="1" />
<file name="weekbarre.png" server="ns2279598.ovh.net" local="130398300000000000" remote="130704808800000000" Dst="1" />
<file name="doris.png" server="ns2279598.ovh.net" local="130401756000000000" remote="130704808800000000" Dst="1" />
<file name="michele.png" server="ns2279598.ovh.net" local="130401756000000000" remote="130704808800000000" Dst="1" />
<file name="bottombarre.png" server="oprlamp001.as44099.net" local="130758949375937828" remote="130717591800000000" Dst="2" />
<file name="boutonbas.png" server="oprlamp001.as44099.net" local="130758949376787877" remote="130717591800000000" Dst="2" />
<file name="boutonbashover.png" server="oprlamp001.as44099.net" local="130758949377437914" remote="130717591800000000" Dst="2" />
<file name="course_schedule_banner.png" server="oprlamp001.as44099.net" local="130758949378647984" remote="130717591800000000" Dst="2" />
<file name="dayofweek.png" server="oprlamp001.as44099.net" local="130758949378657984" remote="130717591800000000" Dst="2" />
<file name="doris.png" server="oprlamp001.as44099.net" local="130758949379588037" remote="130717591800000000" Dst="2" />
<file name="doriszucs.png" server="oprlamp001.as44099.net" local="130758949379988060" remote="130717591800000000" Dst="2" />
<file name="firstweek.png" server="oprlamp001.as44099.net" local="130758949380508090" remote="130717591800000000" Dst="2" />
<file name="footer_img_admissions.jpg" server="oprlamp001.as44099.net" local="130758949382048178" remote="130717591800000000" Dst="2" />
<file name="footer_img_overview.jpg" server="oprlamp001.as44099.net" local="130758949382648212" remote="130717591800000000" Dst="2" />
<file name="footer_img_schedule.png" server="oprlamp001.as44099.net" local="130758949383178243" remote="130717591800000000" Dst="2" />
<file name="footer_img_testimonials.jpg" server="oprlamp001.as44099.net" local="130758949384628326" remote="130717591800000000" Dst="2" />
<file name="fourthweek.png" server="oprlamp001.as44099.net" local="130758949387708502" remote="130717591800000000" Dst="2" />
<file name="homepagepic.png" server="oprlamp001.as44099.net" local="130758949389018577" remote="130717591800000000" Dst="2" />
<file name="homepagebanner.png" server="oprlamp001.as44099.net" local="130758949389378597" remote="130717591800000000" Dst="2" />
<file name="imgweek1.png" server="oprlamp001.as44099.net" local="130758949389818622" remote="130717591800000000" Dst="2" />
<file name="imgweek2.png" server="oprlamp001.as44099.net" local="130758949390478660" remote="130717591800000000" Dst="2" />
<file name="imgweek3.png" server="oprlamp001.as44099.net" local="130758949391078695" remote="130717591800000000" Dst="2" />
<file name="imgweek4.png" server="oprlamp001.as44099.net" local="130758949392378769" remote="130717591800000000" Dst="2" />
<file name="michele.png" server="oprlamp001.as44099.net" local="130758949393108811" remote="130717591800000000" Dst="2" />
<file name="micheleweiss.png" server="oprlamp001.as44099.net" local="130758949393628840" remote="130717591800000000" Dst="2" />
<file name="morebutton.png" server="oprlamp001.as44099.net" local="130758949393998862" remote="130717591800000000" Dst="2" />
<file name="morebutton2.png" server="oprlamp001.as44099.net" local="130758949394728903" remote="130717591800000000" Dst="2" />
<file name="morebutton3.png" server="oprlamp001.as44099.net" local="130758949395248933" remote="130717591800000000" Dst="2" />
<file name="morebutton4.png" server="oprlamp001.as44099.net" local="130758949395948973" remote="130717591800000000" Dst="2" />
<file name="overviewpic.jpg" server="oprlamp001.as44099.net" local="130758949396559008" remote="130717591800000000" Dst="2" />
<file name="scheduleicon.png" server="oprlamp001.as44099.net" local="130758949397309051" remote="130717591800000000" Dst="2" />
<file name="secondweek.png" server="oprlamp001.as44099.net" local="130758949398419114" remote="130717591800000000" Dst="2" />
<file name="soulignage.png" server="oprlamp001.as44099.net" local="130758949398949145" remote="130717591800000000" Dst="2" />
<file name="schedulepic.png" server="oprlamp001.as44099.net" local="130758949398959145" remote="130717591800000000" Dst="2" />
<file name="thirdweek.png" server="oprlamp001.as44099.net" local="130758949399569180" remote="130717591800000000" Dst="2" />
<file name="titre_fondbleu.png" server="oprlamp001.as44099.net" local="130758949400259220" remote="130717591800000000" Dst="2" />
<file name="titre_fondrouge.png" server="oprlamp001.as44099.net" local="130758949401019263" remote="130717591800000000" Dst="2" />
<file name="top_banner_fees.png" server="oprlamp001.as44099.net" local="130758949402529349" remote="130717591800000000" Dst="2" />
<file name="topbarre.png" server="oprlamp001.as44099.net" local="130758949402819366" remote="130717591800000000" Dst="2" />
<file name="top_banner_testimonies.png" server="oprlamp001.as44099.net" local="130758949402839367" remote="130717591800000000" Dst="2" />
<file name="vazquez.png" server="oprlamp001.as44099.net" local="130758949403399399" remote="130717591800000000" Dst="2" />
<file name="weekbarre.png" server="oprlamp001.as44099.net" local="130758949403979432" remote="130717591800000000" Dst="2" />
</dwsync>